football_data_connector-0.9.0.dist-info/METADATA
football_data_connector-0.9.0.dist-info/RECORD
football_data_connector-0.9.0.dist-info/WHEEL
football_data_connector-0.9.0.dist-info/top_level.txt
footballdata/__init__.py
footballdata/connector.py
footballdata/datasets.py
footballdata/utils.py
