Metadata-Version: 2.1
Name: football-data-connector
Version: 0.9.0
Summary: Python package to connect to football-data.org API
Home-page: https://github.com/tony-joseph/football-data-connector
Author: Tony Joseph
Author-email: tony@tonyj.me
License: BSD
Platform: UNKNOWN
Classifier: Development Status :: 3 - Alpha
Classifier: Intended Audience :: Developers
Classifier: License :: OSI Approved :: BSD License
Classifier: Operating System :: OS Independent
Classifier: Programming Language :: Python
Classifier: Programming Language :: Python :: 3 :: Only
Classifier: Programming Language :: Python :: 3.4
Classifier: Programming Language :: Python :: 3.5
Classifier: Programming Language :: Python :: 3.6
Classifier: Topic :: Software Development :: Libraries
Requires-Dist: python-dateutil (>=2.7.3)
Requires-Dist: requests (>=2.19.1)
